LICENSE
README.txt
aditam-server.py
ez_setup.py
setup.cfg
setup.py
aditam/__init__.py
aditam.server.egg-info/PKG-INFO
aditam.server.egg-info/SOURCES.txt
aditam.server.egg-info/dependency_links.txt
aditam.server.egg-info/namespace_packages.txt
aditam.server.egg-info/not-zip-safe
aditam.server.egg-info/requires.txt
aditam.server.egg-info/top_level.txt
aditam/server/__init__.py
aditam/server/loggers.py
aditam/server/manager.py
aditam/server/crontab/__init__.py
aditam/server/crontab/crontab.py
aditam/server/network/__init__.py
aditam/server/network/agentpool.py
aditam/server/network/feedback.py
aditam/server/network/jobpool.py
aditam/server/network/monitoring.py
aditam/server/network/server.py
aditam/server/network/waitingpool.py
aditam/server/tests/__init__.py
aditam/server/tests/test_network.py
debian/README.Debian
debian/changelog
debian/compat
debian/control
debian/copyright
debian/dirs
debian/docs
debian/files
debian/python-aditamserver.aditam-server.default
debian/python-aditamserver.aditam-server.init
debian/rules
samples/aditam-server.conf-sample